{"relative_l_inf_primal_residual":[1.1512977083760274e-8],"instance":"/nfs/sloanlab007/projects/pdopt_proj/instances/lp/miplib2017/fhnw-binschedule0.mps.gz","time_sec_limit":600,"dual_objective":[12632.88896590998],"max_iter":0.0,"relative_l_inf_dual_residual":[6.9443966133064805e-9],"objective_tol":1.0e-8,"termination_reason":["TERMINATION_REASON_OPTIMAL"],"D2_condition_number":[1.0],"alpha":1.1,"initial_tol":1.0e-8,"primal_objective":[12632.88878009805],"l_inf_primal_residual":[5.295969458529726e-7],"relative_optimality_gap":[7.35400185249055e-9],"D1_condition_number":[1.0],"last_iteration":0,"total_time":238.39321899414062,"l_inf_dual_residual":[1.3888793226612961e-8],"blackbox_time":[238.2917308807373],"candidate_type":"POINT_TYPE_AVERAGE_ITERATE"}